sktutor/__about__.py
sktutor/__init__.py
sktutor/pipeline.py
sktutor/preprocessing.py
sktutor/utils.py
sktutor-0.2.3.dist-info/AUTHORS.rst
sktutor-0.2.3.dist-info/LICENSE
sktutor-0.2.3.dist-info/METADATA
sktutor-0.2.3.dist-info/WHEEL
sktutor-0.2.3.dist-info/top_level.txt
sktutor-0.2.3.dist-info/RECORD
