Metadata-Version: 2.1
Name: sktutor
Version: 0.2.3
Summary: sktutor helps your machines learn.
Home-page: https://github.com/dfd/sktutor
Author: Dave Decker
Author-email: dave.decker@gmail.com
License: BSD license
Keywords: sktutor
Classifier: Development Status :: 3 - Alpha
Classifier: Intended Audience :: Developers
Classifier: License :: OSI Approved :: BSD License
Classifier: Natural Language :: English
Classifier: Programming Language :: Python :: 3
Classifier: Programming Language :: Python :: 3.7
Classifier: Programming Language :: Python :: 3.8
Classifier: Programming Language :: Python :: 3.9
License-File: LICENSE
License-File: AUTHORS.rst
Requires-Dist: scipy (>=1.1.0)
Requires-Dist: pandas (>=1.1.5)
Requires-Dist: scikit-learn (>=0.24.2)
Requires-Dist: patsy (>=0.5.1)
